README.md
setup.cfg
setup.py
get_acme_certs.egg-info/PKG-INFO
get_acme_certs.egg-info/SOURCES.txt
get_acme_certs.egg-info/dependency_links.txt
get_acme_certs.egg-info/top_level.txt
src/get_acme_certs.py