Metadata-Version: 2.1
Name: get-acme-certs
Version: 0.1.0
Summary: Extract TLS Certificates from Traefik's acme.json file.
Home-page: https://gitlab.com/rveach/get-acme-certs
Author: Ryan Veach
Author-email: rveach@gmail.com
License: MIT
Keywords: LetsEncrypt,acme.json
Platform: UNKNOWN
Classifier: Development Status :: 4 - Beta
Classifier: Intended Audience :: Developers
Classifier: Intended Audience :: Information Technology
Classifier: Intended Audience :: System Administrators
Classifier: License :: OSI Approved :: MIT License
Classifier: Topic :: Software Development :: Libraries :: Python Modules
Classifier: Topic :: Internet
Classifier: Programming Language :: Python :: 3
Classifier: Programming Language :: Python :: 3.6
Classifier: Programming Language :: Python :: 3.7
Requires-Python: >=3
